plone/app/drafts/__init__.py
plone/app/drafts/behaviors.zcml
plone/app/drafts/configure.zcml
plone/app/drafts/current.py
plone/app/drafts/dexterity.py
plone/app/drafts/dexterity.zcml
plone/app/drafts/draft.py
plone/app/drafts/interfaces.py
plone/app/drafts/lifecycle.py
plone/app/drafts/proxy.py
plone/app/drafts/storage.py
plone/app/drafts/testing.py
plone/app/drafts/tests.py
plone/app/drafts/utils.py
plone/app/drafts/browser/__init__.py
plone/app/drafts/browser/configure.zcml
plone/app/drafts/browser/drafts.pt
plone/app/drafts/browser/overview.pt
plone/app/drafts/browser/targets.pt
plone/app/drafts/browser/tool.gif
plone/app/drafts/browser/view.py
plone/app/drafts/profiles/default/componentregistry.xml
plone/app/drafts/profiles/default/metadata.xml
plone/app/drafts/profiles/default/plone.app.drafts.txt
plone/app/drafts/profiles/default/toolset.xml
plone_app_drafts-3.0.0.dist-info/METADATA
plone_app_drafts-3.0.0.dist-info/WHEEL
plone_app_drafts-3.0.0.dist-info/entry_points.txt
plone_app_drafts-3.0.0.dist-info/top_level.txt
plone_app_drafts-3.0.0.dist-info/RECORD
