Metadata-Version: 2.4
Name: plone.app.drafts
Version: 3.0.0
Summary: Low-level container for draft content
Home-page: http://plone.org
Author: Plone Foundation
Author-email: plone-developers@lists.sourceforge.net
License: GPL
Keywords: plone draft content
Classifier: Development Status :: 4 - Beta
Classifier: Environment :: Web Environment
Classifier: Framework :: Plone
Classifier: Framework :: Plone :: 6.2
Classifier: License :: OSI Approved :: GNU General Public License v2 (GPLv2)
Classifier: Programming Language :: Python
Classifier: Programming Language :: Python :: 3.10
Classifier: Programming Language :: Python :: 3.11
Classifier: Programming Language :: Python :: 3.12
Classifier: Programming Language :: Python :: 3.13
Classifier: Topic :: Internet :: WWW/HTTP
Classifier: Topic :: Internet :: WWW/HTTP :: Dynamic Content
Classifier: Topic :: Software Development :: Libraries :: Python Modules
Requires-Python: >=3.10
Requires-Dist: plone.app.uuid
Requires-Dist: plone.autoform
Requires-Dist: plone.behavior>=1.1
Requires-Dist: plone.dexterity
Requires-Dist: plone.protect
Requires-Dist: plone.uuid
Requires-Dist: Products.CMFCore
Requires-Dist: Products.GenericSetup
Requires-Dist: z3c.form
Requires-Dist: zope.annotation
Requires-Dist: zope.component
Requires-Dist: zope.interface
Requires-Dist: zope.schema
Requires-Dist: Zope
Provides-Extra: test
Requires-Dist: plone.app.contenttypes; extra == "test"
Requires-Dist: plone.app.testing; extra == "test"
Requires-Dist: plone.app.dexterity; extra == "test"
Requires-Dist: plone.testing; extra == "test"
Dynamic: author
Dynamic: author-email
Dynamic: classifier
Dynamic: description
Dynamic: home-page
Dynamic: keywords
Dynamic: license
Dynamic: provides-extra
Dynamic: requires-dist
Dynamic: requires-python
Dynamic: summary
